Workbook

Sheet Executive Dashboard
B2: TOYOTA MOTOR CORPORATION | K2: Evidence-Traceable Analytics
B3: FY2026 Executive Disclosure Dashboard · Fiscal Year Ended March 31, 2026 · Consolidated IFRS | K3: Source: Toyota FY2026 Financial Summary (SEC EDGAR filing)
B6: SALES REVENUES | D6: OPERATING INCOME | F6: OPERATING MARGIN | H6: NET INCOME | J6: OPERATING CASH FLOW | L6: CASH & EQUIVALENTS | N6: VEHICLE UNIT SALES
B7: =Analysis!C10/1000000 -> 50.684952 | D7: =Analysis!C11/1000000 -> 3.766216 | F7: =Analysis!C13 -> 0.074 | H7: =Analysis!C12/1000000 -> 3.848098 | J7: =Analysis!C14/1000000 -> 5.47292 | L7: =Analysis!C15/1000000 -> 12.659622 | N7: =Analysis!C16 -> 9.595
B9: +5.5% YoY | D9: -21.5% YoY | F9: -2.6 pts YoY | H9: -19.2% YoY | J9: +48.0% YoY | L9: +40.9% YoY | N9: FY2026
B11: EXECUTIVE READOUT
B12: MARGIN PRESSURE | F12: NORTH AMERICA | J12: CASH RESILIENCE
B13: Revenue grew 5.5%, but operating income declined 21.5% and margin fell to 7.4%. | F13: Revenue reached ¥21,079.6bn, but the region reported a ¥192.5bn operating loss. | J13: Operating cash flow reached ¥5,472.9bn and cash rose to ¥12,659.6bn, up 40.9%.
B17: PERFORMANCE TRENDS
N18: 💹
N20: 🚘
N27: 🚒
B40: GEOGRAPHIC PROFITABILITY & YEAR-OVER-YEAR CHANGE
N42: 🚔
N49: 🚊
B63: Every KPI reconciles to a primary source document — no fabricated or interpolated figures. Source: Toyota FY2026 Financial Summary (SEC EDGAR filing). Prepared by Daniel Ojo.

Sheet Source Data
A3: TOYOTA MOTOR CORPORATION — SOURCE DATA
A5: Official FY2026 / FY2025 consolidated disclosure inputs
A6: (JPY in millions except volume)
A8: Fiscal Year | B8: Metric | C8: Value | D8: Unit | E8: Basis | F8: Source Document | G8: Page / Section | H8: Source URL
A9: FY2026 | B9: Sales revenues | C9: 50684952 | D9: JPY million | E9: Consolidated IFRS | F9: Toyota FY2026 Financial Summary | G9: p.2, consolidated financial results | H9: https://www.sec.gov/Archives/edgar/data/1094517/000119312526213363/d125424dex991.htm
A10: FY2025 | B10: Sales revenues | C10: 48036704 | D10: JPY million | E10: Consolidated IFRS | F10: Toyota FY2026 Financial Summary | G10: p.2, comparative consolidated financial results | H10: https://www.sec.gov/Archives/edgar/data/1094517/000119312526213363/d125424dex991.htm
A11: FY2026 | B11: Operating income | C11: 3766216 | D11: JPY million | E11: Consolidated IFRS | F11: Toyota FY2026 Financial Summary | G11: p.2, consolidated financial results | H11: https://www.sec.gov/Archives/edgar/data/1094517/000119312526213363/d125424dex991.htm
A12: FY2025 | B12: Operating income | C12: 4795586 | D12: JPY million | E12: Consolidated IFRS | F12: Toyota FY2026 Financial Summary | G12: p.2, comparative consolidated financial results | H12: https://www.sec.gov/Archives/edgar/data/1094517/000119312526213363/d125424dex991.htm
A13: FY2026 | B13: Net income attributable to Toyota | C13: 3848098 | D13: JPY million | E13: Consolidated IFRS | F13: Toyota FY2026 Financial Summary | G13: p.2, consolidated financial results | H13: https://www.sec.gov/Archives/edgar/data/1094517/000119312526213363/d125424dex991.htm
A14: FY2025 | B14: Net income attributable to Toyota | C14: 4765086 | D14: JPY million | E14: Consolidated IFRS | F14: Toyota FY2026 Financial Summary | G14: p.2, comparative consolidated financial results | H14: https://www.sec.gov/Archives/edgar/data/1094517/000119312526213363/d125424dex991.htm
A15: FY2026 | B15: Operating income margin | C15: 0.074 | D15: % | E15: Consolidated IFRS | F15: Toyota FY2026 Financial Summary | G15: p.2, company-reported ratio | H15: https://www.sec.gov/Archives/edgar/data/1094517/000119312526213363/d125424dex991.htm
A16: FY2025 | B16: Operating income margin | C16: 0.1 | D16: % | E16: Consolidated IFRS | F16: Toyota FY2026 Financial Summary | G16: p.2, company-reported ratio | H16: https://www.sec.gov/Archives/edgar/data/1094517/000119312526213363/d125424dex991.htm
A17: FY2026 | B17: Cash flow from operating activities | C17: 5472920 | D17: JPY million | E17: Consolidated IFRS | F17: Toyota FY2026 Financial Summary | G17: p.2, consolidated cash flows | H17: https://www.sec.gov/Archives/edgar/data/1094517/000119312526213363/d125424dex991.htm
A18: FY2025 | B18: Cash flow from operating activities | C18: 3696934 | D18: JPY million | E18: Consolidated IFRS | F18: Toyota FY2026 Financial Summary | G18: p.2, comparative cash flows | H18: https://www.sec.gov/Archives/edgar/data/1094517/000119312526213363/d125424dex991.htm
A19: FY2026 | B19: Cash and cash equivalents | C19: 12659622 | D19: JPY million | E19: Consolidated IFRS | F19: Toyota FY2026 Financial Summary | G19: p.2, consolidated cash flows | H19: https://www.sec.gov/Archives/edgar/data/1094517/000119312526213363/d125424dex991.htm
A20: FY2025 | B20: Cash and cash equivalents | C20: 8982404 | D20: JPY million | E20: Consolidated IFRS | F20: Toyota FY2026 Financial Summary | G20: p.2, comparative cash flows | H20: https://www.sec.gov/Archives/edgar/data/1094517/000119312526213363/d125424dex991.htm
A21: FY2026 | B21: Consolidated vehicle unit sales | C21: 9.595 | D21: Million units | E21: Consolidated global volume | F21: Toyota FY2026 Financial Summary | G21: p.2, financial-results narrative | H21: https://www.sec.gov/Archives/edgar/data/1094517/000119312526213363/d125424dex991.htm

Sheet Geographic Data
A3: TOYOTA MOTOR CORPORATION — GEOGRAPHIC DATA
A5: FY2026 regional disclosure inputs
A6: (JPY in billions)
A8: Fiscal Year | B8: Region | C8: Sales Revenue | D8: Operating Income | E8: Unit | F8: Source Document | G8: Page / Section | H8: Source URL
A9: FY2026 | B9: Japan | C9: 22074.1 | D9: 2321 | E9: JPY billion | F9: Toyota FY2026 Financial Summary | G9: p.3, Geographic Information | H9: https://www.sec.gov/Archives/edgar/data/1094517/000119312526213363/d125424dex991.htm
A10: FY2026 | B10: North America | C10: 21079.6 | D10: -192.5 | E10: JPY billion | F10: Toyota FY2026 Financial Summary | G10: p.3, Geographic Information | H10: https://www.sec.gov/Archives/edgar/data/1094517/000119312526213363/d125424dex991.htm
A11: FY2026 | B11: Europe | C11: 6701.1 | D11: 357.7 | E11: JPY billion | F11: Toyota FY2026 Financial Summary | G11: p.3, Geographic Information | H11: https://www.sec.gov/Archives/edgar/data/1094517/000119312526213363/d125424dex991.htm
A12: FY2026 | B12: Asia | C12: 9271.3 | D12: 869.8 | E12: JPY billion | F12: Toyota FY2026 Financial Summary | G12: p.3, Geographic Information | H12: https://www.sec.gov/Archives/edgar/data/1094517/000119312526213363/d125424dex991.htm
A13: FY2026 | B13: Other regions | C13: 4758.9 | D13: 328.9 | E13: JPY billion | F13: Toyota FY2026 Financial Summary | G13: p.3, Geographic Information | H13: https://www.sec.gov/Archives/edgar/data/1094517/000119312526213363/d125424dex991.htm

Sheet Analysis
A3: TOYOTA MOTOR CORPORATION — ANALYSIS
A5: Source-linked calculations for executive dashboard
A6: (JPY in millions unless noted)
A8: CONSOLIDATED PERFORMANCE
A9: Metric | B9: FY2025A | C9: FY2026A | D9: YoY Change
A10: Sales revenues | B10: ='Source Data'!C10 -> 48036704 | C10: ='Source Data'!C9 -> 50684952 | D10: =C10/B10-1 -> 0.055129678
A11: Operating income | B11: ='Source Data'!C12 -> 4795586 | C11: ='Source Data'!C11 -> 3766216 | D11: =C11/B11-1 -> -0.21464947
A12: Net income | B12: ='Source Data'!C14 -> 4765086 | C12: ='Source Data'!C13 -> 3848098 | D12: =C12/B12-1 -> -0.19243892
A13: Operating margin | B13: ='Source Data'!C16 -> 0.1 | C13: ='Source Data'!C15 -> 0.074 | D13: =C13/B13-1 -> -0.26
A14: Operating cash flow | B14: ='Source Data'!C18 -> 3696934 | C14: ='Source Data'!C17 -> 5472920 | D14: =C14/B14-1 -> 0.48039429
A15: Cash and cash equivalents | B15: ='Source Data'!C20 -> 8982404 | C15: ='Source Data'!C19 -> 12659622 | D15: =C15/B15-1 -> 0.40938016
A16: Vehicle unit sales | B16: n/a | C16: ='Source Data'!C21 -> 9.595 | D16: n/a
A26: GEOGRAPHIC PERFORMANCE — FY2026
A27: Region | B27: Sales Revenue | C27: Operating Income | D27: Operating Margin
A28: ='Geographic Data'!B9 -> Japan | B28: ='Geographic Data'!C9 -> 22074.1 | C28: ='Geographic Data'!D9 -> 2321 | D28: =C28/B28 -> 0.10514585
A29: ='Geographic Data'!B10 -> North America | B29: ='Geographic Data'!C10 -> 21079.6 | C29: ='Geographic Data'!D10 -> -192.5 | D29: =C29/B29 -> -0.0091320518
A30: ='Geographic Data'!B11 -> Europe | B30: ='Geographic Data'!C11 -> 6701.1 | C30: ='Geographic Data'!D11 -> 357.7 | D30: =C30/B30 -> 0.053379296
A31: ='Geographic Data'!B12 -> Asia | B31: ='Geographic Data'!C12 -> 9271.3 | C31: ='Geographic Data'!D12 -> 869.8 | D31: =C31/B31 -> 0.093816401
A32: ='Geographic Data'!B13 -> Other regions | B32: ='Geographic Data'!C13 -> 4758.9 | C32: ='Geographic Data'!D13 -> 328.9 | D32: =C32/B32 -> 0.06911261

Sheet KPI Summary
A3: TOYOTA — KPI SUMMARY
A5: Source-linked executive measures and calculated comparisons
A6: (JPY in millions unless stated)
A8: Metric | B8: FY2025A | C8: FY2026A | D8: YoY Change | E8: Source Basis
A9: =Analysis!A10 -> Sales revenues | B9: =Analysis!B10 -> 48036704 | C9: =Analysis!C10 -> 50684952 | D9: =Analysis!D10 -> 0.055129678 | E9: Official Toyota FY2026 Financial Summary
A10: =Analysis!A11 -> Operating income | B10: =Analysis!B11 -> 4795586 | C10: =Analysis!C11 -> 3766216 | D10: =Analysis!D11 -> -0.21464947 | E10: Official Toyota FY2026 Financial Summary
A11: =Analysis!A12 -> Net income | B11: =Analysis!B12 -> 4765086 | C11: =Analysis!C12 -> 3848098 | D11: =Analysis!D12 -> -0.19243892 | E11: Official Toyota FY2026 Financial Summary
A12: =Analysis!A13 -> Operating margin | B12: =Analysis!B13 -> 0.1 | C12: =Analysis!C13 -> 0.074 | D12: =Analysis!D13 -> -0.26 | E12: Official Toyota FY2026 Financial Summary
A13: =Analysis!A14 -> Operating cash flow | B13: =Analysis!B14 -> 3696934 | C13: =Analysis!C14 -> 5472920 | D13: =Analysis!D14 -> 0.48039429 | E13: Official Toyota FY2026 Financial Summary
A14: =Analysis!A15 -> Cash and cash equivalents | B14: =Analysis!B15 -> 8982404 | C14: =Analysis!C15 -> 12659622 | D14: =Analysis!D15 -> 0.40938016 | E14: Official Toyota FY2026 Financial Summary
A15: =Analysis!A16 -> Vehicle unit sales | B15: =Analysis!B16 -> n/a | C15: =Analysis!C16 -> 9.595 | D15: n/a | E15: Official Toyota FY2026 Financial Summary

Sheet Data Dictionary
A3: TOYOTA — DATA DICTIONARY
A5: Metric definitions, units, and reporting basis
A6: (Disclosure-based dashboard)
A8: Field | B8: Definition | C8: Unit | D8: Basis
A9: Sales revenues | B9: Toyota consolidated sales revenues under IFRS. | C9: JPY million | D9: Consolidated IFRS
A10: Operating income | B10: Toyota consolidated operating income under IFRS. | C10: JPY million | D10: Consolidated IFRS
A11: Operating margin | B11: Operating income divided by sales revenues, company-reported. | C11: % | D11: Consolidated IFRS
A12: Vehicle unit sales | B12: Global consolidated vehicle unit sales. | C12: Million units | D12: Consolidated volume
A13: Geographic revenue / operating income | B13: Sales revenue and operating income reported by geography. | C13: JPY billion | D13: Geographic disclosure

Sheet Source Register
A3: TOYOTA — SOURCE REGISTER
A5: Official disclosure URLs used for the audited dashboard source layer
A6: (Primary sources only)
A8: Source Document | B8: Reporting Period | C8: Primary Use | D8: URL
A9: Toyota FY2026 Financial Summary | B9: FY2026, ended 31 March 2026 | C9: Consolidated, cash-flow, and geographic metrics | D9: https://www.sec.gov/Archives/edgar/data/1094517/000119312526213363/d125424dex991.htm
A10: Toyota Financial Results Archive | B10: FY2021–FY2026 archive | C10: Official access point for current and historical materials | D10: https://global.toyota/en/ir/financial-results/archives/03.html

Sheet Dashboard Data
A1: Metric | B1: YoY Change | G1: FY2025A
A2: =Analysis!A10 -> Sales revenues | B2: =Analysis!D10 -> 0.055129678 | G2: FY2026A
A3: =Analysis!A11 -> Operating income | B3: =Analysis!D11 -> -0.21464947
A4: =Analysis!A12 -> Net income | B4: =Analysis!D12 -> -0.19243892
A5: =Analysis!A14 -> Operating cash flow | B5: =Analysis!D14 -> 0.48039429
A6: =Analysis!A15 -> Cash and cash equivalents | B6: =Analysis!D15 -> 0.40938016
